[
  {
    "name": "Standing Light Punch",
    "name_ja": "立ち弱パン",
    "alternativeNames": ["Jab"],
    "alternativeNames_ja": ["小パン", "コパン"],
    "slug": "ryu-stand-light-punch",
    "abbreviation": "S.LP",
    "abbeviation_ja": "立ち弱P",
    "characterId": 0,
    "type": "normal",
    "damage": 300,
    "hitCount": 1,
    "guardLevel": "high",
    "input": "5lp",
    "cancelsInto": ["chain", "special", "super"],
    "chainsInto": ["5lp", "2lp", "2lk"],
    "frameCount": ["S-3", "A-6", "R-13"],
    "frameAdvantage": {"hit": 4, "block": -1},
    "notes": [],
    "notes_ja": []
  },
  {
    "name": "Standing Medium Punch",
    "name_ja": "立ち中パン",
    "alternativeNames": ["Strong"],
    "alternativeNames_ja": ["中パン"],
    "slug": "ryu-stand-medium-punch",
    "abbreviation": "S.MP",
    "abbeviation_ja": "立ち中P",
    "characterId": 0,
    "type": "normal",
    "damage": 600,
    "hitCount": 1,
    "guardLevel": "high",
    "input": "5mp",
    "cancelsInto": ["special", "super", "targetCombo"],
    "chainsInto": ["5mp", "2mp"],
    "frameCount": ["S-5", "A-9", "R-20"],
    "frameAdvantage": {"hit": 7, "block": -1}
  },
  {
    "name": "Standing Heavy Punch",
    "name_ja": "立ち強パン",
    "alternativeNames": ["Fierce"],
    "alternativeNames_ja": ["大パン"],
    "slug": "ryu-stand-heavy-punch",
    "abbreviation": "S.HP",
    "abbeviation_ja": "立ち強P",
    "characterId": 0,
    "type": "normal",
    "damage": 800,
    "hitCount": 1,
    "guardLevel": "high",
    "input": "5hp",
    "cancelsInto": ["special", "super", "targetCombo"],
    "chainsInto": [],
    "frameCount": ["S-9", "A-14", "R-32"],
    "frameAdvantage": {"hit": 3, "block": -2},
    "properties": ["forcesStanding"]
  },
  {
    "name": "Standing Light Kick",
    "name_ja": "立ち弱キック",
    "alternativeNames": ["Short"],
    "alternativeNames_ja": ["小足", "コアシ"],
    "slug": "ryu-stand-light-kick",
    "abbreviation": "S.LK",
    "abbeviation_ja": "立ち弱K",
    "characterId": 0,
    "type": "normal",
    "damage": 300,
    "hitCount": 1,
    "guardLevel": "low",
    "input": "5lk",
    "cancelsInto": ["chain", "special", "super"],
    "chainsInto": [],
    "frameCount": ["S-4", "A-7", "R-18"],
    "frameAdvantage": {"hit": 2, "block": -4}
  },
  {
    "name": "Standing Medium Kick",
    "name_ja": "立ち中キック",
    "alternativeNames": ["Forward"],
    "alternativeNames_ja": ["中足", "中アシ"],
    "slug": "ryu-stand-medium-kick",
    "abbreviation": "S.MK",
    "abbeviation_ja": "立ち中K",
    "characterId": 0,
    "type": "normal",
    "damage": 700,
    "hitCount": 1,
    "guardLevel": "high",
    "input": "5mk",
    "cancelsInto": [],
    "chainsInto": [],
    "frameCount": ["S-8", "A-11", "R-29"],
    "frameAdvantage": {"hit": 4, "block": -4}
  },
  {
    "name": "Standing Heavy Kick",
    "name_ja": "立ち強キック",
    "alternativeNames": ["Roundhouse"],
    "alternativeNames_ja": ["大足", "大アシ"],
    "slug": "ryu-stand-heavy-kick",
    "abbreviation": "S.HK",
    "abbeviation_ja": "立ち強K",
    "characterId": 0,
    "type": "normal",
    "damage": 900,
    "hitCount": 1,
    "guardLevel": "high",
    "input": "5hk",
    "cancelsInto": [],
    "chainsInto": [],
    "frameCount": ["S-11", "A-15", "R-35"],
    "frameAdvantage": {"hit": 9, "block": 1}
  },
  {
        "name": "Crouching Light Punch",
    "name_ja": "しゃがみ弱パン",
    "alternativeNames": ["Crouching jab"],
    "alternativeNames_ja": ["しゃがみ小パン", "しゃがみコパン"],
    "slug": "ryu-crouch-light-punch",
    "abbreviation": "C.LP",
    "abbeviation_ja": "屈弱P",
    "characterId": 0,
    "type": "normal",
    "damage": 300,
    "hitCount": 1,
    "guardLevel": "low",
    "input": "2lp",
    "cancelsInto": ["chain", "special", "super"],
    "chainsInto": ["5lp", "2lp", "2lk"],
    "frameCount": ["S-3", "A-5", "R-14"],
    "frameAdvantage": {"hit": 4, "block": -1}
  },
  {
    "name": "Crouching Medium Punch",
    "name_ja": "しゃがみ中パン",
    "alternativeNames": ["Crouching jab"],
    "alternativeNames_ja": ["しゃがみ中パン"],
    "slug": "ryu-crouch-medium-punch",
    "abbreviation": "C.MP",
    "abbeviation_ja": "屈中P",
    "characterId": 0,
    "type": "normal",
    "damage": 700,
    "hitCount": 1,
    "guardLevel": "low",
    "input": "2mp",
    "cancelsInto": ["special", "super"],
    "chainsInto": [],
    "frameCount": ["S-5", "A-8", "R-22"],
    "frameAdvantage": {"hit": 5, "block": 0}
  },
  {
    "name": "Crouching Heavy Punch",
    "name_ja": "しゃがみ強パン",
    "alternativeNames": ["Crouching strong"],
    "alternativeNames_ja": ["しゃがみ大パン"],
    "slug": "ryu-crouch-heavy-punch",
    "abbreviation": "C.HP",
    "abbeviation_ja": "屈強P",
    "characterId": 0,
    "type": "normal",
    "damage": 900,
    "hitCount": 1,
    "guardLevel": "low",
    "input": "2hp",
    "cancelsInto": ["special", "super"],
    "chainsInto": [],
    "frameCount": ["S-8", "A-12", "R-34"],
    "frameAdvantage": {"hit": 3, "block": -7}
  },
  {
    "name": "Crouching Light Kick",
    "name_ja": "しゃがみ弱キック",
    "alternativeNames": ["Crouching short"],
    "alternativeNames_ja": ["しゃがみ小足", "しゃがみコアシ"],
    "slug": "ryu-crouch-light-kick",
    "abbreviation": "C.LK",
    "abbeviation_ja": "屈弱K",
    "characterId": 0,
    "type": "normal",
    "damage": 200,
    "hitCount": 1,
    "guardLevel": "low",
    "input": "2lk",
    "cancelsInto": ["chain"],
    "chainsInto": ["5lp", "2lp", "2lk"],
    "frameCount": ["S-4", "A-6", "R-16"],
    "frameAdvantage": {"hit": 3, "block": -3}
  },
  {
    "name": "Crouching Medium Kick",
    "name_ja": "しゃがみ中キック",
    "slug": "ryu-crouch-medium-kick",
    "abbreviation": "C.MK",
    "abbeviation_ja": "屈中K",
    "characterId": 0,
    "type": "normal",
    "damage": 500,
    "hitCount": 1,
    "guardLevel": "low",
    "input": "2mk",
    "cancelsInto": ["special", "super"],
    "chainsInto": [],
    "frameCount": ["S-7", "A-10", "R-29"],
    "frameAdvantage": {"hit": 1, "block": -6}
  },
  {
    "name": "Crouching Heavy Kick",
    "name_ja": "しゃがみ強キック",
    "alternativeNames": ["Crouching forward"],
    "alternativeNames_ja": ["しゃがみ大足", "しゃがみ大アシ"],
    "slug": "ryu-crouch-heavy-kick",
    "abbreviation": "C.HK",
    "abbeviation_ja": "屈強K",
    "characterId": 0,
    "type": "normal",
    "damage": 900,
    "hitCount": 1,
    "guardLevel": "low",
    "input": "2hk",
    "cancelsInto": [],
    "chainsInto": [],
    "frameCount": ["S-8", "A-11", "R-34"],
    "frameAdvantage": {"hit": 32, "block": -11}
  },
  {
    "name": "Jumping Light Punch",
    "name_ja": "ジャンプ弱パン",
    "alternativeNames": ["Crouching forward"],
    "alternativeNames_ja": ["ジャンプ小パン", "ジャンプコパン"],
    "slug": "ryu-jump-light-punch",
    "abbreviation": "J.LP",
    "abbeviation_ja": "ジャンプ弱P",
    "characterId": 0,
    "type": "normal",
    "damage": 300,
    "hitCount": 1,
    "guardLevel": "high",
    "input": "jlp",
    "cancelsInto": [],
    "chainsInto": [],
    "frameCount": ["S-3", "A-13"]
  },
  {
    "name": "Jumping Medium Punch",
    "slug": "ryu-jump-medium-punch",
    "abbreviation": "J.MP",
    "name_ja": "ジャンプ中パン",
    "abbeviation_ja": "ジャンプ中P",
    "characterId": 0,
    "type": "normal",
    "damage": 700,
    "hitCount": 2,
    "guardLevel": "high",
    "input": "jmp",
    "cancelsInto": ["special"],
    "chainsInto": [],
    "frameCount": ["S-7", "A-12"]
  },
  {
    "name": "Jumping Heavy Punch",
    "name_ja": "ジャンプ強パン",
    "alternativeNames": ["Jumping roundhouse"],
    "alternativeNames_ja": ["ジャンプ大パン"],
    "slug": "ryu-jump-heavy-punch",
    "abbreviation": "J.HP",
    "abbeviation_ja": "ジャンプ強P",
    "characterId": 0,
    "type": "normal",
    "damage": 800,
    "hitCount": 1,
    "guardLevel": "high",
    "input": "jhp",
    "cancelsInto": [],
    "chainsInto": [],
    "frameCount": ["S-8", "A-14"]
  },
  {
    "name": "Jumping Light Kick",
    "slug": "ryu-jump-light-kick",
    "abbreviation": "J.LK",
    "name_ja": "ジャンプ弱キック",
    "abbeviation_ja": "ジャンプ弱K",
    "characterId": 0,
    "type": "normal",
    "damage": 300,
    "hitCount": 1,
    "guardLevel": "high",
    "input": "jlk",
    "cancelsInto": [],
    "chainsInto": [],
    "frameCount": ["S-5", "A-15"],
    "properties": ["canCrossUp"]
  },
  {
    "name": "Jumping Medium Kick",
    "name_ja": "ジャンプ中キック",
    "alternativeNames": ["Jumping forward"],
    "alternativeNames_ja": ["ジャンプ中足", "ジャンプ中アシ"],
    "slug": "ryu-jump-medium-kick",
    "abbreviation": "J.MK",
    "abbeviation_ja": "ジャンプ中K",
    "characterId": 0,
    "type": "normal",
    "damage": 500,
    "hitCount": 1,
    "guardLevel": "high",
    "input": "jmk",
    "cancelsInto": [],
    "chainsInto": [],
    "frameCount": ["S-6", "A-12"],
    "properties": ["canCrossUp"]
  },
  {
    "name": "Jumping Heavy Kick",
    "name_ja": "ジャンプ強キック",
    "alternativeNames": ["Jumping roundhouse"],
    "alternativeNames_ja": ["ジャンプ大足", "ジャンプ大アシ"],
    "slug": "ryu-jump-heavy-kick",
    "abbreviation": "J.HK",
    "abbeviation_ja": "ジャンプ強K",
    "characterId": 0,
    "type": "normal",
    "damage": 500,
    "hitCount": 1,
    "guardLevel": "high",
    "input": "jhk",
    "cancelsInto": [],
    "chainsInto": [],
    "frameCount": ["S-11", "A-19"]
  },
  {
    "name": "Collarbone Breaker",
    "name_ja": "鎖骨割り",
    "slug": "collarbone-breaker",
    "characterId": 0,
    "type": "commandNormal",
    "damage": 600,
    "hitCount": 2,
    "guardLevel": "high",
    "input": "6mp",
    "cancelsInto": [],
    "chainsInto": [],
    "frameCount": ["S-20", "A-24", "R-42"],
    "frameAdvantage": {"hit": 2, "block": -3}
  },
  {
    "name": "Solar Plexus Strike",
    "name_ja": "鳩尾砕き",
    "slug": "solar-plexus-strike",
    "characterId": 0,
    "type": "commandNormal",
    "damage": 800,
    "hitCount": 2,
    "guardLevel": "high",
    "input": "6hp",
    "cancelsInto": [],
    "chainsInto": [],
    "frameCount": ["S-19", "A-24", "R-40"],
    "frameAdvantage": {"hit": 6, "block": 1}
  },
  {
    "name": "Short Uppercut",
    "name_ja": "上げ突き",
    "slug": "short-uppercut",
    "characterId": 0,
    "type": "commandNormal",
    "damage": 800,
    "hitCount": 1,
    "guardLevel": "high",
    "input": "4hp",
    "cancelsInto": ["special", "super"],
    "chainsInto": [],
    "frameCount": ["S-6", "A-9", "R-35"],
    "frameAdvantage": {"hit": 1, "block": -13},
    "properties": ["forcesStanding"]
  },
  {
    "name": "Whirlwind Kick",
    "name_ja": "旋風脚",
    "slug": "whirlwind-kick",
    "characterId": 0,
    "type": "commandNormal",
    "damage": 800,
    "hitCount": 1,
    "guardLevel": "high",
    "input": "6hk",
    "cancelsInto": ["special"],
    "chainsInto": [],
    "frameCount": ["S-15", "A-19", "R-39"],
    "frameAdvantage": {"hit": 2, "block": -4}
  },
  {
    "name": "Axe Kick",
    "name_ja": "かかと落とし",
    "slug": "axe-kick",
    "characterId": 0,
    "type": "commandNormal",
    "damage": 800,
    "hitCount": 2,
    "guardLevel": "high",
    "input": "4hk",
    "cancelsInto": ["special", "super"],
    "chainsInto": [],
    "frameCount": ["S-9", "A-14", "R-19", "A-22", "R-43"],
    "frameAdvantage": {"hit": 0, "block": -4}
  },
  {
    "name": "High Double Strike",
    "name_ja": "上段二連撃",
    "slug": "high-double-strike",
    "characterId": 0,
    "type": "targetCombo",
    "damage": 1800,
    "hitCount": 2,
    "guardLevel": "high",
    "input": "5hp>5hk",
    "cancelsInto": [],
    "chainsInto": [],
    "frameCount": ["S-9", "A-14", "R-16", "S-24", "A-28", "R-48"],
    "frameAdvantage": {"hit": 36, "block": -8},
    "properties": ["knockdown"]
  },
  {
    "name": "Fuwa Double Strike",
    "name_ja": "不破二連撃",
    "slug": "fuwa-double-strike",
    "characterId": 0,
    "type": "targetCombo",
    "damage": 900,
    "hitCount": 2,
    "guardLevel": "high",
    "input": "5mp>5lk",
    "cancelsInto": [],
    "chainsInto": [],
    "frameCount": ["S-5", "A-9", "R-11", "S-15", "A-18", "R-34"],
    "frameAdvantage": {"hit": 1, "block": -7}
  },
  {
    "name": "Fuwa Triple Strike",
    "name_ja": "不破三連撃",
    "slug": "fuwa-triple-strike",
    "characterId": 0,
    "type": "targetCombo",
    "damage": 1620,
    "hitCount": 3,
    "guardLevel": "high",
    "input": "5mp>5lk>5hk",
    "cancelsInto": [],
    "chainsInto": [],
    "frameCount": ["S-5", "A-9", "R-11", "S-15", "A-16", "S-32", "A-36", "R-56"],
    "frameAdvantage": {"hit": 36, "block": -8}
  },
  {
    "name": "Hadoken (Light)",
    "name_ja": "波動拳 (弱)",
    "slug": "ryu-hadoken-light",
    "characterId": 0,
    "type": "special",
    "damage": 600,
    "hitCount": 1,
    "guardLevel": "high",
    "input": "236lp",
    "cancelsInto": ["super3"],
    "frameCount": ["S-15", "PA-16", "R-47"],
    "frameAdvantage": {"hit": -1, "block": -5},
    "notes": [
      "Frame data is for point blank range."
    ],
    "notes_ja": [
      "フレームデータはゼロ距離の場合。"
    ]
  },
  {
    "name": "Hadoken (Medium)",
    "name_ja": "波動拳 (中)",
    "slug": "ryu-hadoken-medium",
    "characterId": 0,
    "type": "special",
    "damage": 600,
    "hitCount": 1,
    "guardLevel": "high",
    "input": "236mp",
    "cancelsInto": ["super3"],
    "frameCount": ["S-13", "PA-14", "R-47"],
    "frameAdvantage": {"hit": -3, "block": -7},
    "notes": [
      "Frame data is for point blank range."
    ],
    "notes_ja": [
      "フレームデータはゼロ距離の場合。"
    ]
  },
  {
    "name": "Hadoken (Heavy)",
    "name_ja": "波動拳 (強)",
    "slug": "ryu-hadoken-heavy",
    "characterId": 0,
    "type": "special",
    "damage": 600,
    "hitCount": 1,
    "guardLevel": "high",
    "input": "236hp",
    "cancelsInto": ["super"],
    "frameCount": ["S-11","PA-12", "R-47"],
    "frameAdvantage": {"hit": -5, "block": -9},
    "notes": [
      "Frame data is for point blank range."
    ],
    "notes_ja": [
      "フレームデータはゼロ距離の場合。"
    ]
  },
  {
    "name": "Hadoken (OD)",
    "name_ja": "波動拳 (OD)",
    "slug": "ryu-hadoken-od",
    "characterId": 0,
    "type": "special",
    "damage": 800,
    "hitCount": 2,
    "guardLevel": "high",
    "input": "236[pp]",
    "cancelsInto": ["super3", "super2"],
    "frameCount": ["S-11", "PA-12", "R-40"],
    "frameAdvantage": {"hit": 54, "block": -1},
    "notes": [
      "Frame data is for point blank range."
    ],
    "notes_ja": [
      "フレームデータはゼロ距離の場合。"
    ]
  },
  {
    "name": "Denjin Hadoken",
    "name_ja": "電刃波動拳",
    "slug": "denjin-hadoken",
    "characterId": 0,
    "type": "special",
    "damage": 800,
    "hitCount": 2,
    "guardLevel": "high",
    "input": "236p",
    "cancelsInto": ["super3"],
    "chainsInto": [],
    "frameCount": ["S-11", "PA-12", "R-42"],
    "frameAdvantage": {"hit": 52, "block": -3},
    "properties": ["stockDecrement"],
    "parentSlug": "denjin-charge",
    "notes": [
      "Frame data is for point blank range."
    ],
    "notes_ja": [
      "フレームデータはゼロ距離の場合。"
    ]
  },
  {
    "name": "Denjin Hadoken (OD)",
    "name_ja": "電刃波動拳 (OD)",
    "slug": "denjin-hadoken-od",
    "characterId": 0,
    "type": "special",
    "damage": 1000,
    "hitCount": 3,
    "guardLevel": "high",
    "input": "236[pp]",
    "cancelsInto": ["super2", "super3"],
    "chainsInto": [],
    "frameCount": ["S-11", "PA-12", "R-42"],
    "frameAdvantage": {"hit": 57, "block": 2},
    "properties": ["stockDecrement"],
    "parentSlug": "denjin-charge",
    "notes": [
      "Frame data is for point blank range."
    ],
    "notes_ja": [
      "フレームデータはゼロ距離の場合。"
    ]
  },
  {
    "name": "Shoryuken (Light)",
    "name_ja": "昇龍拳（弱)",
    "slug": "ryu-shoryuken-light",
    "alternativeNames": ["Dragon Punch", "DP", "Shoryu"],
    "characterId": 0,
    "type": "special",
    "damage": 1100,
    "hitCount": 1,
    "guardLevel": "high",
    "input": "623lp",
    "cancelsInto": ["super3"],
    "frameCount": ["S-4", "A-14", "R-47"],
    "frameAdvantage": {"hit": 38, "block": -21},
    "invincibilityFrames": {
      "airStart": 1,
      "airEnd": 14
    }
  },
  {
    "name": "Shoryuken (Medium)",
    "name_ja": "昇龍拳（中)",
    "slug": "ryu-shoryuken-medium",
    "alternativeNames": ["Dragon Punch", "DP", "Shoryu"],
    "characterId": 0,
    "type": "special",
    "damage": 1200,
    "hitCount": 1,
    "guardLevel": "high",
    "input": "623mp",
    "cancelsInto": ["super3"],
    "frameCount": ["S-5", "A-15", "R-57"],
    "frameAdvantage": {"hit": 34, "block": -30},
    "invincibilityFrames": {
      "airStart": 1,
      "airEnd": 15
    }
  },
  {
    "name": "Shoryuken (Heavy)",
    "name_ja": "昇龍拳（強)",
    "slug": "ryu-shoryuken-hp",
    "alternativeNames": ["Dragon Punch", "DP", "Shoryu"],
    "characterId": 0,
    "type": "special",
    "damage": 1400,
    "hitCount": 1,
    "guardLevel": "high",
    "input": "623hp",
    "cancelsInto": ["super3"],
    "frameCount": ["S-6", "A-16", "R-65"],
    "frameAdvantage": {"hit": 29, "block": -37},
    "invincibilityFrames": {
      "airStart": 1,
      "airEnd": 16
    }
  },
  {
    "name": "Shoryuken (OD)",
    "name_ja": "昇龍拳 (OD)",
    "slug": "ryu-shoryuken-od",
    "alternativeNames": ["Dragon Punch", "DP", "Shoryu"],
    "characterId": 0,
    "type": "special",
    "damage": 1600,
    "hitCount": 2,
    "guardLevel": "high",
    "input": "623[pp]",
    "frameCount": ["S-6", "A-16", "R-68"],
    "frameAdvantage": {"hit": 29, "block": -40},
    "invincibilityFrames": {
      "start": 2,
      "end": 6,
      "airStart": 7,
      "airEnd": 10
    }
  },
  {
    "name": "Tatsumaki Senpukyaku (Light)",
    "slug": "ryu-tatsumaki-senpukyaku-light",
    "alternativeNames": ["Hurricane Kick", "Tatsu"],
    "name_ja": "竜巻旋風脚 (弱)",
    "characterId": 0,
    "type": "special",
    "damage": 800,
    "hitCount": 1,
    "guardLevel": "high",
    "input": "214lk",
    "frameCount": ["S-11", "A-14", "R-46"],
    "frameAdvantage": {"hit": 35, "block": -14}
  },
  {
    "name": "Tatsumaki Senpukyaku (Medium)",
    "name_ja": "竜巻旋風脚 (中)",
    "slug": "ryu-tatsumaki-senpukyaku-medium",
    "alternativeNames": ["Hurricane Kick", "Tatsu"],
    "characterId": 0,
    "type": "special",
    "damage": 900,
    "hitCount": 2,
    "guardLevel": "high",
    "input": "214mk",
    "frameCount": ["S-13", "A-15", "R-28", "A-30", "R-61"],
    "frameAdvantage": {"hit": 61, "block": -12}
  },
  {
    "name": "Tatsumaki Senpukyaku (Heavy)",
    "name_ja": "竜巻旋風脚 (強)",
    "slug": "ryu-tatsumaki-senpukyaku-heavy",
    "alternativeNames": ["Hurricane Kick", "Tatsu"],
    "characterId": 0,
    "type": "special",
    "damage": 1000,
    "hitCount": 3,
    "guardLevel": "high",
    "input": "214hk",
    "frameCount": ["S-15", "A-17", "R-30", "A-32", "R-45", "A-47", "R-78"],
    "frameAdvantage": {"hit": 105, "block": -12}
  },
  {
    "name": "Tatsumaki Senpukyaku (OD)",
    "name_ja": "竜巻旋風脚 (OD)",
    "slug": "ryu-tatsumaki-senpukyaku-od",
    "alternativeNames": ["Hurricane Kick", "Tatsu"],
    "characterId": 0,
    "type": "special",
    "damage": "1000",
    "hitCount": 5,
    "guardLevel": "high",
    "input": "214[kk]",
    "frameCount": ["S-12", "A-14", "R-18", "A-20", "R-24", "A-26", "R-29", "A-31", "R-35", "A-37", "R-60"],
    "frameAdvantage": {"hit": 57, "block": -14}
  },
  {
    "name": "Aerial Tatsumaki Senpukyaku",
    "name_ja": "空中竜巻旋風脚",
    "slug": "aerial-tatsumaki-senpukyaku",
    "alternativeNames": ["Air Tatsu"],
    "characterId": 0,
    "type": "special",
    "damage": 900,
    "hitCount": 3,
    "guardLevel": "high",
    "input": "j214k",
    "cancelsInto": [],
    "chainsInto": [],
    "frameCount": ["S-10", "A-12", "R-17", "A-19", "R-25", "A-27"],
    "frameAdvantage": {"hit": 48, "block": -1},
    "properties": ["canCrossUp", "knockdown"]
  },
  {
    "name": "Aerial Tatsumaki Senpukyaku (OD)",
    "name_ja": "空中竜巻旋風脚 (OD)",
    "slug": "aerial-ryu-tatsumaki-senpukyaku-od",
    "alternativeNames": ["EX Air Tatsu"],
    "characterId": 0,
    "type": "special",
    "damage": 1500,
    "hitCount": 4,
    "guardLevel": "high",
    "input": "j214[kk]",
    "cancelsInto": [],
    "chainsInto": [],
    "frameCount": ["S-10", "A-12", "R-13", "A-16", "R-17", "A-20", "R-21", "A-24", "R-26", "A-28"],
    "frameAdvantage": {"hit": 47, "block": -16}
  },
  {
    "name": "High Blade Kick (Light)",
    "name_ja": "上段足刀蹴り (弱)",
    "slug": "high-blade-kick-light",
    "alternativeNames": ["Donkey Kick"],
    "characterId": 0,
    "type": "special",
    "damage": 1000,
    "hitCount": 1,
    "guardLevel": "high",
    "input": "236lk",
    "cancelsInto": ["super"],
    "chainsInto": [],
    "frameCount": ["S-14", "A-23", "R-45"],
    "frameAdvantage": {"hit": 35, "block": -11}
  },
  {
    "name": "High Blade Kick (Medium)",
    "name_ja": "上段足刀蹴り (中)",
    "slug": "high-blade-kick-medium",
    "alternativeNames": ["Donkey Kick"],
    "characterId": 0,
    "type": "special",
    "damage": 1100,
    "hitCount": 1,
    "guardLevel": "high",
    "input": "236mk",
    "cancelsInto": ["super"],
    "chainsInto": [],
    "frameCount": ["S-17", "A-26", "R-45"],
    "frameAdvantage": {"hit": 40, "block": -8}
  },
  {
    "name": "High Blade Kick (Heavy)",
    "name_ja": "上段足刀蹴り (強)",
    "slug": "high-blade-kick-heavy",
    "alternativeNames": ["Donkey Kick"],
    "characterId": 0,
    "type": "special",
    "damage": 1300,
    "hitCount": 1,
    "guardLevel": "high",
    "input": "236hk",
    "cancelsInto": ["super"],
    "chainsInto": [],
    "frameCount": ["S-28", "A-37", "R-53"],
    "frameAdvantage": {"hit": 45, "block": -5}
  },
  {
    "name": "High Blade Kick (OD)",
    "name_ja": "上段足刀蹴り (OD)",
    "slug": "high-blade-kick-od",
    "alternativeNames": ["EX Donkey Kick"],
    "characterId": 0,
    "type": "special",
    "damage": 800,
    "hitCount": 1,
    "guardLevel": "high",
    "input": "236[kk]",
    "cancelsInto": ["special", "super"],
    "chainsInto": [],
    "frameCount": ["S-18", "A-23", "R-55"],
    "frameAdvantage": {"hit": 45, "block": -18}
  },
  {
    "name": "Hashogeki (Light)",
    "name_ja": "波掌撃（弱)",
    "slug": "hashogeki-light",
    "characterId": 0,
    "type": "special",
    "damage": 700,
    "hitCount": 1,
    "guardLevel": "high",
    "input": "214lp",
    "cancelsInto": ["super3"],
    "chainsInto": [],
    "frameCount": ["S-11", "A-17", "R-35"],
    "frameAdvantage": {"hit": 2, "block": -4}
  },
  {
    "name": "Hashogeki (Medium)",
    "name_ja": "波掌撃（中)",
    "slug": "hashogeki-medium",
    "characterId": 0,
    "type": "special",
    "damage": 800,
    "hitCount": 1,
    "guardLevel": "high",
    "input": "214mp",
    "cancelsInto": ["super3"],
    "chainsInto": [],
    "frameCount": ["S-18", "A-24", "R-41"],
    "frameAdvantage": {"hit": 2, "block": -5}
  },
  {
    "name": "Hashogeki (Heavy)",
    "name_ja": "波掌撃（強)",
    "slug": "hashogeki-heavy",
    "characterId": 0,
    "type": "special",
    "damage": 800,
    "hitCount": 2,
    "guardLevel": "high",
    "input": "214hp",
    "cancelsInto": ["super3"],
    "chainsInto": [],
    "frameCount": ["S-29", "A-35", "R-54"],
    "frameAdvantage": {"hit": 61, "block": 2}
  },
  {
    "name": "Hashogeki (OD)",
    "name_ja": "波掌撃 (OD)",
    "slug": "hashogeki-od",
    "characterId": 0,
    "type": "special",
    "damage": 900,
    "hitCount": 1,
    "guardLevel": "high",
    "input": "214[pp]",
    "cancelsInto": ["super2", "super3"],
    "chainsInto": [],
    "frameCount": ["S-17", "A-23", "R-43"],
    "frameAdvantage": {"hit": 3, "block": 3}
  },
  {
    "name": "Denjin Hashogeki",
    "name_ja": "電刃波掌撃",
    "slug": "denjin-hashogeki",
    "characterId": 0,
    "type": "special",
    "damage": 800,
    "hitCount": 2,
    "guardLevel": "high",
    "input": "214p",
    "cancelsInto": ["super3"],
    "chainsInto": [],
    "frameCount": ["S-20", "A-26", "R-44"],
    "frameAdvantage": {"hit": 62, "block": 3},
    "properties": ["stockDecrement"],
    "parentSlug": "denjin-charge"
  },
  {
    "name": "Denjin Hashogeki (OD)",
    "name_ja": "電刃波掌撃 (OD)",
    "slug": "denjin-hashogeki-od",
    "characterId": 0,
    "type": "special",
    "damage": 600,
    "hitCount": 1,
    "guardLevel": "high",
    "input": "214[pp]",
    "cancelsInto": ["super2", "super3"],
    "chainsInto": [],
    "frameCount": ["S-17", "A-23", "R-42"],
    "frameAdvantage": {"hit": 87, "block": 4},
    "properties": ["stockDecrement"],
    "parentSlug": "denjin-charge"
  },
  {
    "name": "Shinku Hadoken",
    "name_ja": "真空波動拳",
    "slug": "shinku-hadoken",
    "characterId": 0,
    "type": "super1",
    "damage": 2000,
    "hitCount": 5,
    "guardLevel": "high",
    "input": "236236p",
    "cancelsInto": [],
    "chainsInto": [],
    "frameCount": ["S-6", "PA-24", "R-31", "PA-32", "R-39", "PA-40", "R-47", "PA-48", "R-55", "PA-56"],
    "frameAdvantage": {"hit": 26, "block": -24},
    "invincibilityFrames": {
      "start": 1,
      "end": 1,
      "strikeStart": 2,
      "strikeEnd": 6
    }
  },
  {
    "name": "Denjin Shinku Hadoken",
    "name_ja": "電刃真空波動拳",
    "slug": "denjin-shinku-hadoken",
    "characterId": 0,
    "type": "super1",
    "damage": 2400,
    "hitCount": 4,
    "guardLevel": "high",
    "input": "236236p",
    "cancelsInto": [],
    "chainsInto": [],
    "frameCount": ["S-6", "PA-26", "R-33", "PA-34", "R-41", "PA-42", "R-49", "PA-50", "R-57", "PA-58"],
    "frameAdvantage": {"hit": 27, "block": -24},
    "properties": ["stockDecrement"],
    "parentSlug": "denjin-charge",
    "invincibilityFrames": {
      "start": 1,
      "end": 1,
      "strikeStart": 2,
      "strikeEnd": 6
    }
  },
  {
    "name": "Shin Hashogeki (No charge)",
    "name_ja": "真波掌撃 (溜めなし)",
    "slug": "shin-hashogeki-no-charge",
    "characterId": 0,
    "type": "super2",
    "damage": 2600,
    "hitCount": 1,
    "guardLevel": "high",
    "input": "214214p",
    "cancelsInto": [],
    "chainsInto": [], 
    "frameCount": ["S-11", "PA-17", "R-56"],
    "frameAdvantage": {"hit": 78, "block": -20},
    "properties": ["armorBreak"]
  },
  {
    "name": "Shin Hashogeki (Level 1)",
    "name_ja": "真波掌撃 (溜め1段階)",
    "slug": "shin-hashogeki-level-1",
    "characterId": 0,
    "type": "super2",
    "damage": 2800,
    "hitCount": 1,
    "guardLevel": "high",
    "input": "214214(p)",
    "cancelsInto": [],
    "chainsInto": [],
    "frameCount": ["S-20", "A-26", "R-65"],
    "frameAdvantage": {"hit": 78, "block": -20}
  },
  {
    "name": "Shin Hashogeki (Level 2)",
    "name_ja": "真波掌撃 (溜め2段階)",
    "slug": "shin-hashogeki-level-2",
    "characterId": 0,
    "type": "super2",
    "damage": 3000,
    "hitCount": 1,
    "guardLevel": "high",
    "input": "214214(p)",
    "cancelsInto": [],
    "chainsInto": [],
    "frameCount": ["S-49", "A-55", "R-94"],
    "frameAdvantage": {"hit": 78, "block": -20}
  },
  {
    "name": "Denjin Shin Hashogeki (No charge)",
    "name_ja": "電刃真波掌撃 (溜めなし)",
    "slug": "denjin-shin-hashogeki-no-charge",
    "characterId": 0,
    "type": "super2",
    "damage": 3000,
    "hitCount": 1,
    "guardLevel": "high",
    "input": "214214(p)",
    "cancelsInto": [],
    "chainsInto": [],
    "frameCount": ["S-11", "A-17", "R-56"],
    "frameAdvantage": {"hit": 78, "block": -20},
    "properties": ["stockDecrement"],
    "parentSlug": "denjin-charge"
  },
  {
    "name": "Denjin Shin Hashogeki (Level 1)",
    "name_ja": "電刃真波掌撃 (溜め1段階)",
    "slug": "denjin-shin-hashogeki-level-1",
    "characterId": 0,
    "type": "super2",
    "damage": 3200,
    "hitCount": 1,
    "guardLevel": "high",
    "input": "214214(p)",
    "cancelsInto": [],
    "chainsInto": [],
    "frameCount": ["S-20", "A-26", "R-65"],
    "frameAdvantage": {"hit": 78, "block": -20},
    "properties": ["stockDecrement"],
    "parentSlug": "denjin-charge"
  },
  {
    "name": "Denjin Shin Hashogeki (Level 2)",
    "name_ja": "電刃真波掌撃 (溜め2段階)",
    "slug": "denjin-shin-hashogeki-level-2",
    "characterId": 0,
    "type": "super2",
    "damage": 3400,
    "hitCount": 1,
    "guardLevel": "high",
    "input": "214214(p)",
    "cancelsInto": [],
    "chainsInto": [],
    "frameCount": ["S-49", "A-25", "R-64"],
    "frameAdvantage": {"hit": 78, "block": -20},
    "properties": ["stockDecrement"],
    "parentSlug": "denjin-charge"
  },
  {
    "name": "Shin Shoryuken",
    "name_ja": "真昇竜拳",
    "slug": "shin-shoryuken",
    "characterId": 0,
    "type": "super3",
    "damage": 4000,
    "hitCount": 1,
    "guardLevel": "high",
    "input": "236236k",
    "cancelsInto": [],
    "chainsInto": [],
    "frameCount": ["S-4", "A-16", "R-48"],
    "frameAdvantage": {"hit": 8, "block": -52},
    "invincibilityFrames": {"start": 1, "end": 16}
  },
  {
    "name": "Shin Shoryuken (Critical Art)",
    "name_ja": "真昇竜拳 (CA)",
    "slug": "shin-ryu-shoryuken-ca",
    "characterId": 0,
    "type": "super3",
    "damage": 4500,
    "hitCount": 1,
    "guardLevel": "high",
    "input": "236236k",
    "cancelsInto": [],
    "chainsInto": [],
    "frameCount": ["S-4", "A-16", "R-48"],
    "frameAdvantage": {"hit": 8, "block": -52},
    "invincibilityFrames": {"start": 1, "end": 16}
  },
  {
    "name": "Shoulder Throw",
    "name_ja": "背負い投げ",
    "slug": "shoulder-throw",
    "alternativeNames": ["Forward Throw"],
    "alternativeNames_ja": ["前投げ"],
    "characterId": 0,
    "type": "throw",
    "damage": 1200,
    "hitCount": 1,
    "input": "[lplk]",
    "cancelsInto": [],
    "chainsInto": [],
    "frameCount": ["S-3", "A-6", "R-29"],
    "frameAdvantage": {"hit": 18}
  },
  {
    "name": "Somersault Throw",
    "name_ja": "巴投げ",
    "slug": "somersault-throw",
    "alternativeNames": ["Back Throw"],
    "alternativeNames_ja": ["後ろ投げ"],
    "characterId": 0,
    "type": "throw",
    "damage": 1200,
    "hitCount": 1,
    "input": "[4lplk]",
    "cancelsInto": [],
    "chainsInto": [],
    "frameCount": ["S-4", "A-7", "R-30"],
    "frameAdvantage": {"hit": 11}
  },
  {
    "name": "Denjin Charge",
    "name_ja": "電刃錬気",
    "slug": "denjin-charge",
    "characterId": 0,
    "type": "special",
    "damage": 0,
    "hitCount": 0,
    "input": "22p",
    "cancelsInto": [],
    "chainsInto": [],
    "frameCount": ["S-52"],
    "properties": ["stockIncrement"]
  }
]
